nexus/__init__.py
nexus/cli.py
nexus/integrations/__init__.py
nexus/knowledge/__init__.py
nexus/knowledge/search.py
nexus/knowledge/vault.py
nexus/research/__init__.py
nexus/research/pdf.py
nexus/research/zotero.py
nexus/teaching/__init__.py
nexus/teaching/courses.py
nexus/teaching/quarto.py
nexus/utils/__init__.py
nexus/utils/config.py
nexus/utils/tutorial.py
nexus/writing/__init__.py
nexus/writing/bibliography.py
nexus/writing/manuscript.py
nexus_cli-0.5.1.dist-info/METADATA
nexus_cli-0.5.1.dist-info/WHEEL
nexus_cli-0.5.1.dist-info/entry_points.txt
nexus_cli-0.5.1.dist-info/RECORD
